nftools/__init__.py
nftools/__main__.py
nftools/create_whitelist_token.py
nftools/download.py
nftools/objects.py
nftools/solana.py
nftools/types.py
nftools/utils.py
nftools/types/__init__.py
nftools/types/metaplex.py
nftools-1.1.2.dist-info/AUTHORS.rst
nftools-1.1.2.dist-info/LICENSE
nftools-1.1.2.dist-info/METADATA
nftools-1.1.2.dist-info/WHEEL
nftools-1.1.2.dist-info/entry_points.txt
nftools-1.1.2.dist-info/top_level.txt
nftools-1.1.2.dist-info/RECORD
