Metadata-Version: 2.1
Name: nftools
Version: 1.1.2
Summary: A CLI for managing your solana nft collection.
Home-page: https://github.com/akajimeagle/nftools
Author: Jim Eagle
Author-email: akajimeagle@pm.me
License: MIT license
Keywords: nftools
Platform: UNKNOWN
Classifier: Development Status :: 2 - Pre-Alpha
Classifier: Intended Audience :: Developers
Classifier: License :: OSI Approved :: MIT License
Classifier: Natural Language :: English
Classifier: Programming Language :: Python :: 3
Classifier: Programming Language :: Python :: 3.7
Classifier: Programming Language :: Python :: 3.8
Classifier: Programming Language :: Python :: 3.9
Requires-Python: >=3.7
License-File: LICENSE
License-File: AUTHORS.rst
Requires-Dist: click (~=8.1.3)
Requires-Dist: aiohttp (~=3.8.1)
Requires-Dist: base58 (~=2.1.1)
Requires-Dist: pandas (~=1.3.5)
Requires-Dist: requests (~=2.28.1)
Requires-Dist: setuptools (~=60.2.0)
Requires-Dist: tqdm (==4.64.0)
Requires-Dist: aiolimiter (~=1.0.0)
